README.txt
setup.py
model/__init__.py
model/column.py
model/criteria.py
model/database.py
model/locator.py
model/model.py
model/type.py
pyactiverecord.egg-info/PKG-INFO
pyactiverecord.egg-info/SOURCES.txt
pyactiverecord.egg-info/dependency_links.txt
pyactiverecord.egg-info/requires.txt
pyactiverecord.egg-info/top_level.txt
pyactiverecord.egg-info/zip-safe