Metadata-Version: 1.1
Name: pyactiverecord
Version: 0.2.3
Summary: pyactiverecord is python active record like mysql wrapper.
Home-page: https://github.com/nkdn/pyactiverecord
Author: Hiroyuki Nikaido
Author-email: hiroyuki.nikaido@gmail.com
License: MIT
Keywords: db,mysql,active record,ORM
Platform: UNKNOWN
Classifier: Development Status :: 3 - Alpha
Classifier: Environment :: Console
Classifier: Intended Audience :: Developers
Classifier: Natural Language :: English
Classifier: Operating System :: OS Independent
Classifier: Programming Language :: Python
Classifier: Topic :: Software Development :: Libraries :: Python Modules
Classifier: Topic :: Internet :: WWW/HTTP :: Dynamic Content :: CGI Tools/Libraries
Classifier: Topic :: Utilities
Classifier: License :: OSI Approved :: MIT License
